{
  "phase": "implement",
  "session_id": "2026-06-09T0000-sprintc147",
  "ts": "2026-06-09T23:29:54Z",
  "files_touched": [
    "qor/scripts/session.py",
    "qor/scripts/orchestration_override.py",
    "qor/scripts/cycle_count_escalator.py",
    "qor/scripts/check_shadow_threshold.py",
    "docs/FEATURE_INDEX.md",
    "README.md",
    "tests/test_session_id_path_safety.py",
    "tests/test_feature_index_citations_resolve.py"
  ],
  "commits": [],
  "test_summary": {
    "new": 7,
    "deterministic": true
  },
  "ai_provenance": {
    "system": "Qor-logic",
    "version": "0.107.2",
    "host": "unknown",
    "model_family": "opus",
    "human_oversight": "absent",
    "ts": "2026-06-09T23:29:54Z"
  }
}